nonebot_plugin_pixivbot/__init__.py
nonebot_plugin_pixivbot/config.py
nonebot_plugin_pixivbot/context.py
nonebot_plugin_pixivbot/data/__init__.py
nonebot_plugin_pixivbot/data/errors.py
nonebot_plugin_pixivbot/data/interval_task_repo.py
nonebot_plugin_pixivbot/data/local_tag.py
nonebot_plugin_pixivbot/data/nb_session.py
nonebot_plugin_pixivbot/data/pixiv_binding.py
nonebot_plugin_pixivbot/data/pixiv_repo/__init__.py
nonebot_plugin_pixivbot/data/pixiv_repo/base.py
nonebot_plugin_pixivbot/data/pixiv_repo/compressor.py
nonebot_plugin_pixivbot/data/pixiv_repo/enums.py
nonebot_plugin_pixivbot/data/pixiv_repo/errors.py
nonebot_plugin_pixivbot/data/pixiv_repo/lazy_illust.py
nonebot_plugin_pixivbot/data/pixiv_repo/local_repo/__init__.py
nonebot_plugin_pixivbot/data/pixiv_repo/local_repo/base.py
nonebot_plugin_pixivbot/data/pixiv_repo/local_repo/dummy.py
nonebot_plugin_pixivbot/data/pixiv_repo/local_repo/file.py
nonebot_plugin_pixivbot/data/pixiv_repo/local_repo/sql.py
nonebot_plugin_pixivbot/data/pixiv_repo/local_repo/sql_models.py
nonebot_plugin_pixivbot/data/pixiv_repo/mediator.py
nonebot_plugin_pixivbot/data/pixiv_repo/mediator_repo.py
nonebot_plugin_pixivbot/data/pixiv_repo/models.py
nonebot_plugin_pixivbot/data/pixiv_repo/remote_repo.py
nonebot_plugin_pixivbot/data/source/__init__.py
nonebot_plugin_pixivbot/data/source/lifecycle_mixin.py
nonebot_plugin_pixivbot/data/source/migration_manager.py
nonebot_plugin_pixivbot/data/source/sql/__init__.py
nonebot_plugin_pixivbot/data/source/sql/meta_info.py
nonebot_plugin_pixivbot/data/source/sql/migration/__init__.py
nonebot_plugin_pixivbot/data/source/sql/migration/sql_v1_to_v2.py
nonebot_plugin_pixivbot/data/source/sql/migration/sql_v2_to_v3.py
nonebot_plugin_pixivbot/data/source/sql/migration/sql_v3_to_v4.py
nonebot_plugin_pixivbot/data/source/sql/migration/sql_v4_to_v5.py
nonebot_plugin_pixivbot/data/subscription.py
nonebot_plugin_pixivbot/data/utils/__init__.py
nonebot_plugin_pixivbot/data/utils/shortuuid.py
nonebot_plugin_pixivbot-2.1.6.dist-info/LICENSE
nonebot_plugin_pixivbot-2.1.6.dist-info/METADATA
nonebot_plugin_pixivbot-2.1.6.dist-info/WHEEL
nonebot_plugin_pixivbot-2.1.6.dist-info/RECORD
