Metadata-Version: 2.3
Name: nonebot-plugin-pixivbot
Version: 2.1.6
Summary: Nonebot Plugin PixivBot
License: MIT
Author: ssttkkl
Author-email: huang.wen.long@hotmail.com
Requires-Python: >=3.9,<4.0
Classifier: License :: OSI Approved :: MIT License
Classifier: Programming Language :: Python :: 3
Classifier: Programming Language :: Python :: 3.9
Classifier: Programming Language :: Python :: 3.10
Classifier: Programming Language :: Python :: 3.11
Classifier: Programming Language :: Python :: 3.12
Classifier: Programming Language :: Python :: 3.13
Requires-Dist: Pillow (>=10.3.0)
Requires-Dist: PixivPy-Async (>=1.2.14,<2.0.0)
Requires-Dist: SQLAlchemy[asyncio] (>=2.0.0,<3.0.0)
Requires-Dist: aiofiles (>=23.2.1)
Requires-Dist: aiosqlite (>=0.18.0)
Requires-Dist: asyncache (>=0.3.1)
Requires-Dist: cachetools (>=5.2.0)
Requires-Dist: frozendict (>=2.3.4)
Requires-Dist: lazy (>=1.4,<2.0)
Requires-Dist: nonebot-plugin-access-control (>=1.2,<2.0)
Requires-Dist: nonebot-plugin-localstore (>=0.5.1)
Requires-Dist: nonebot-plugin-send-anything-anywhere (>=0.3.0)
Requires-Dist: nonebot-plugin-session (>=0.2.0)
Requires-Dist: nonebot-plugin-session-orm (>=0.1.1)
Requires-Dist: nonebot-plugin-session-saa (>=0.1.0)
Requires-Dist: nonebot2 (>=2.3,<3.0)
Requires-Dist: nonebot_plugin_apscheduler (>=0.3.0)
Requires-Dist: numpy (>=1.23.1)
Requires-Dist: pytz (>=2024.2)
Requires-Dist: shortuuid (>=1.0.9)
Requires-Dist: ssttkkl-nonebot-utils (>=0.1.23)
Requires-Dist: tzlocal (>=5.0.1)
Project-URL: Repository, https://github.com/ssttkkl/nonebot-plugin-pixivbot
